{
  "total": 1,
  "data": [
    {
      "id": 33177,
      "codigo_registro": "P0034518",
      "tipo_documento": "DNI",
      "numero_documento": "70053388",
      "apellido_paterno": "GALINDO",
      "apellido_materno": "HUAMAN",
      "nombres": "DAVID JAVIER",
      "nombre_completo": "DAVID JAVIER GALINDO HUAMAN",
      "email": "dgalindoh@unmsm.edu.pe",
      "orcid": "0000-0003-1112-268X",
      "cti_vitae": "34518",
      "grupo": "N",
      "nivel": "III",
      "condicion": "Activo",
      "institucion_laboral_principal": "UNIVERSIDAD NACIONAL MAYOR DE SAN MARCOS",
      "institucion_laboral_actual": "UNIVERSIDAD NACIONAL MAYOR DE SAN MARCOS",
      "genero": "Masculino",
      "fecha_inicio_vigencia": "12/05/2026",
      "fecha_fin_vigencia": "12/05/2028",
      "fecha_registro_activo": "12/05/2026",
      "fecha_ingreso_renacyt": "27/07/2021",
      "fecha_ultima_prod_cientifica": "01/02/2026",
      "calificaciones_previas": "RENACYT 2021,-,III,72.0,12/05/2026,12/05/2026- | RENACYT 2021,-,IV,57.0,06/12/2023,06/12/2023-15/05/2026 | RENACYT 2021,-,V,39.0,18/05/2022,18/05/2022-06/12/2023 | RENACYT 2018,MR,II,,26/07/2021,26/07/2021-18/05/2022",
      "_raw": {
        "id": 33177,
        "codigoRegistro": "P0034518",
        "tipoDocumento": "DNI",
        "numeroDocumento": "70053388",
        "apellidoPaterno": "GALINDO",
        "apellidoMaterno": "HUAMAN",
        "nombres": "DAVID JAVIER",
        "emailNotificar": "dgalindoh@unmsm.edu.pe",
        "orcid": "0000-0003-1112-268X",
        "ctiVitae": "34518",
        "hojaRuta": "2026006922",
        "fechaEnvioConstancia": "15/05/2026",
        "grupo": "N",
        "nivel": "III",
        "fechaInicioVigencia": "12/05/2026",
        "fechaFinVigencia": "12/05/2028",
        "rutaDocumento": "/opt/renacyt/constancias_registro_firmadas/P0034518_271212.pdf",
        "anulado": false,
        "institucionLaboralPrincipal": "UNIVERSIDAD NACIONAL MAYOR DE SAN MARCOS",
        "institucionLaboralActual": "UNIVERSIDAD NACIONAL MAYOR DE SAN MARCOS",
        "areasOcde": "1F14-1F07-1F08-4C01",
        "genero": "Masculino",
        "condicion": "Activo",
        "fechaRegistroActivo": "12/05/2026",
        "solicitudId": 271212,
        "convocatoriaId": 6,
        "fechaAnulacion": null,
        "fechaInicioVigenciaAnt": "06/12/2023",
        "fechaFinVigenciaAnt": "06/12/2025",
        "grupoAnt": "N",
        "nivelAnt": "IV",
        "fechaExclusion": null,
        "estado": null,
        "flagOrcid": false,
        "fechaActualizacionOrcid": null,
        "contactable": true,
        "entidadMicroNormalizada": "",
        "fechaIngresoRenacyt": "27/07/2021",
        "fechaUltimaProdCientifica": "01/02/2026",
        "actosRegistrales": null,
        "calificacionesPrevias": "RENACYT 2021,-,III,72.0,12/05/2026,12/05/2026- | RENACYT 2021,-,IV,57.0,06/12/2023,06/12/2023-15/05/2026 | RENACYT 2021,-,V,39.0,18/05/2022,18/05/2022-06/12/2023 | RENACYT 2018,MR,II,,26/07/2021,26/07/2021-18/05/2022"
      }
    }
  ]
}
